{
  "AppServer": "replace-with-web-url",
  "ApiServer": "replace-with-api-url",
  "AuditServer": "https://samplesaas.azurewebsites.net",
  "GoogleApiKey": "<GoogleAPIKey>",
  "dateFormatLong": "DD MMM yyyy HH:mm:ss",
  "dateFormatMedium": "DD MMM yyy HH:mm",
  "dateFormatShort": "DD MMM yyyy",
  "Authentication": {
    "Authority": "https://samplesaas-staging.eu.auth0.com/",
    "ClientId": "<ClientId>",
    "ApiAudience": "https://samplesaas-api.com",
    "Auth0OrgId": "",
    "AuthFlow": "CODE",
    "LoginUrl": "",
    "LogoutUrl": "https://samplesaas-staging.eu.auth0.com/v2/logout",
    "TokenUrl": "",
    "RevocationUrl": "",
    "SilentRefresh": true,
    "BYOI": {
      "Enabled": false,
      "Kid": "",
      "PubKeyUrl": "",
      "UseDiscovery": true,
      "UseExternalRoles": false
    }
  },
  "PdfUrl": "https://samplesaas-function.azurewebsites.net/api/GeneratePdf"
}
